Workbook

Sheet OpenPosition_10_28_2026
A1: Open Positions
A2: As of October 28, 2026 · Highlighted rows were sold in October
A3: Color key: Hard-coded input Formula Link to another tab Link to external file
A5: Symbol | B5: Description | C5: Asset Class | D5: Sector | E5: Status | F5: Quantity | G5: Currency | H5: LastPrice | I5: PricePaid | J5: DayChange | K5: ProfitLoss | L5: MarketValue | M5: ProfitLoss % | N5: Investment | O5: Weight
A6: BTC | B6: Bitcoin | C6: Digital Assets | D6: Digital Assets | E6: Held | F6: 2 | G6: USD | H6: 81423.94 | I6: 79635.47 | J6: 0 | K6: 3576.94 | L6: 162847.88 | M6: 2.25 | N6: =I6*F6 -> 159270.94 | O6: =N6/$N$61 -> 0.12548376
A7: QQQM | B7: Invesco Exchange-Traded Fund Trust II - Invesco NASDAQ 100 ETF | C7: Equity ETF | D7: US Broad Market | E7: Held | F7: 500 | G7: USD | H7: 296.96 | I7: 247.09 | J7: 3.7 | K7: 24935 | L7: 148480 | M7: 20.18 | N7: =I7*F7 -> 123545 | O7: =N7/$N$61 -> 0.097336599
A8: IWM | B8: BlackRock Institutional Trust Company N.A. - iShares Russell 2000 ETF | C8: Equity ETF | D8: US Small Cap | E8: Held | F8: 425 | G8: USD | H8: 280.18 | I8: 208.21 | J8: 3.19 | K8: 30587.25 | L8: 119076.5 | M8: 34.57 | N8: =I8*F8 -> 88489.25 | O8: =N8/$N$61 -> 0.069717452
A9: RSP | B9: Invesco Capital Management LLC - Invesco S&P 500 Equal Weight ETF | C9: Equity ETF | D9: US Broad Market | E9: Held | F9: 500 | G9: USD | H9: 217.52 | I9: 172.41 | J9: 0.23 | K9: 22555 | L9: 108760 | M9: 26.16 | N9: =I9*F9 -> 86205 | O9: =N9/$N$61 -> 0.067917775
A10: SCO | B10: ProShares Trust - ProShares UltraShort Bloomberg Crude Oil -2x Shares | C10: Leveraged / Inverse ETF | D10: Energy | E10: Held | F10: 2500 | G10: USD | H10: 16.25 | I10: 32.16 | J10: 0.13 | K10: -39775 | L10: 40625 | M10: -49.47 | N10: =I10*F10 -> 80400 | O10: =N10/$N$61 -> 0.063344227
A11: IYF | B11: BlackRock Institutional Trust Company N.A. - iShares U.S. Financials ETF | C11: Equity ETF | D11: Financials | E11: Held | F11: 690 | G11: USD | H11: 130.25 | I11: 113.40899 | J11: -0.18 | K11: 11620.3 | L11: 89872.5 | M11: 14.85 | N11: =I11*F11 -> 78252.2 | O11: =N11/$N$61 -> 0.061652054
A12: IYK | B12: BlackRock Institutional Trust Company N.A. - iShares U.S. Consumer Staples ETF | C12: Equity ETF | D12: Consumer Staples | E12: Held | F12: 1000 | G12: USD | H12: 76.44 | I12: 71.31 | J12: -0.74 | K12: 5130 | L12: 76440 | M12: 7.19 | N12: =I12*F12 -> 71310 | O12: =N12/$N$61 -> 0.056182548
A13: EUAD | B13: Select STOXX Europe Aerospace & Defense ETF | C13: Equity ETF | D13: Industrials | E13: Held | F13: 1250 | G13: USD | H13: 39.32 | I13: 41.05 | J13: 0.2 | K13: -2162.5 | L13: 49150 | M13: -4.21 | N13: =I13*F13 -> 51312.5 | O13: =N13/$N$61 -> 0.040427247
A14: TLT | B14: BlackRock Institutional Trust Company N.A. - iShares 20+ Year Treasury Bond ETF | C14: Fixed Income | D14: Fixed Income | E14: Held | F14: 500 | G14: USD | H14: 81.63 | I14: 92.53 | J14: -0.05 | K14: -5450 | L14: 40815 | M14: -11.78 | N14: =I14*F14 -> 46265 | O14: =N14/$N$61 -> 0.036450506
A15: SPY | B15: SSgA Active Trust - SPDR S&P 500 ETF Trust | C15: Equity ETF | D15: US Broad Market | E15: Held | F15: 75 | G15: USD | H15: 769.66 | I15: 587.84 | J15: 4.29 | K15: 13636.5 | L15: 57724.5 | M15: 30.93 | N15: =I15*F15 -> 44088 | O15: =N15/$N$61 -> 0.034735327
A16: TNA | B16: Direxion Shares ETF Trust - Direxion Daily Small Cap Bull 3X Shares | C16: Leveraged / Inverse ETF | D16: US Small Cap | E16: Sold Oct-26 | F16: 1000 | G16: USD | H16: 58.34 | I16: 40 | J16: 1.92 | K16: 18340 | L16: 58340 | M16: 45.85 | N16: =I16*F16 -> 40000 | O16: =N16/$N$61 -> 0.031514541
A17: INDA | B17: BlackRock Institutional Trust Company N.A. - iShares MSCI India ETF | C17: Equity ETF | D17: International / EM | E17: Held | F17: 600 | G17: USD | H17: 46.74 | I17: 55.49 | J17: 0.15 | K17: -5250 | L17: 28044 | M17: -15.77 | N17: =I17*F17 -> 33294 | O17: =N17/$N$61 -> 0.026231128
... A60: SOXX | B60: BlackRock Institutional Trust Company N.A. - iShares Semiconductor ETF | C60: Equity ETF | D60: Technology | E60: Sold Oct-26 | F60: -40 | G60: USD | H60: 511.06 | I60: 489.37 | J60: 19.23 | K60: -867.6 | L60: 20442.4 | M60: -4.43 | N60: =I60*F60 -> -19574.8 | O60: =N60/$N$61 -> -0.015422271
A61: Total | K61: =SUM(K6:K60) -> 87210.94 | L61: =SUM(L6:L60) -> 1435985.9 | N61: =SUM(N6:N60) -> 1269255.4 | O61: =SUM(O6:O60) -> 1

Sheet Rebalance Oct-26
A1: October Rebalance
A2: Positions sold this month and where the $180K went
A3: Color key: Hard-coded input Formula Link to another tab Link to external file
A5: 1 · Sold this month (highlighted rows)
A6: Symbol | B6: Description | C6: Quantity | D6: LastPrice | E6: Proceeds | F6: Cost Basis | G6: Realized P/L
A7: =OpenPosition_10_28_2026!A16 -> TNA | B7: =OpenPosition_10_28_2026!B16 -> Direxion Shares ETF Trust - Direxion Daily Small Cap Bull 3X Shares | C7: =OpenPosition_10_28_2026!F16 -> 1000 | D7: =OpenPosition_10_28_2026!H16 -> 58.34 | E7: =C7*D7 -> 58340 | F7: =OpenPosition_10_28_2026!N16 -> 40000 | G7: =OpenPosition_10_28_2026!K16 -> 18340
A8: =OpenPosition_10_28_2026!A20 -> UNH | B8: =OpenPosition_10_28_2026!B20 -> Unitedhealth Group Inc | C8: =OpenPosition_10_28_2026!F20 -> 100 | D8: =OpenPosition_10_28_2026!H20 -> 410.39 | E8: =C8*D8 -> 41039 | F8: =OpenPosition_10_28_2026!N20 -> 30167 | G8: =OpenPosition_10_28_2026!K20 -> 10872
A9: =OpenPosition_10_28_2026!A60 -> SOXX | B9: =OpenPosition_10_28_2026!B60 -> BlackRock Institutional Trust Company N.A. - iShares Semiconductor ETF | C9: =OpenPosition_10_28_2026!F60 -> -40 | D9: =OpenPosition_10_28_2026!H60 -> 511.06 | E9: =C9*D9 -> -20442.4 | F9: =OpenPosition_10_28_2026!N60 -> -19574.8 | G9: =OpenPosition_10_28_2026!K60 -> -867.6
A10: Total sold | E10: =SUM(E7:E9) -> 78936.6 | F10: =SUM(F7:F9) -> 50592.2 | G10: =SUM(G7:G9) -> 28344.4
A11: SOXX was a short (−40 sh), so closing it uses cash: its proceeds show as negative.
A13: 2 · Reinvested
A14: Allocation | B14: Asset Class | C14: Sector | D14: Status | E14: Amount | F14: % of Total
A15: SpaceX | B15: Private Markets | C15: Industrials | D15: Allocated | E15: 30000 | F15: =E15/$E$22 -> 0.16666667
A16: Anthropic | B16: Private Markets | C16: Technology | D16: Planned | E16: 30000 | F16: =E16/$E$22 -> 0.16666667
A17: Industrials | B17: Equity ETF | C17: Industrials | D17: Allocated | E17: 30000 | F17: =E17/$E$22 -> 0.16666667
A18: Real Estate | B18: Equity ETF | C18: Real Estate | D18: Allocated | E18: 15000 | F18: =E18/$E$22 -> 0.083333333
A19: Materials | B19: Equity ETF | C19: Materials | D19: Allocated | E19: 30000 | F19: =E19/$E$22 -> 0.16666667
A20: Regional Banks | B20: Equity ETF | C20: Financials | D20: Allocated | E20: 20000 | F20: =E20/$E$22 -> 0.11111111
A21: Biotech | B21: Equity ETF | C21: Health Care | D21: Allocated | E21: 25000 | F21: =E21/$E$22 -> 0.13888889
A22: Total reinvested | E22: =SUM(E15:E21) -> 180000 | F22: =SUM(F15:F21) -> 1
A23: Amounts as provided by you. Anthropic is marked Planned ("going to allocate"); SpaceX and Anthropic classed as Private Markets.
A25: 3 · Sources & uses
A26: Item | E26: Amount
A27: Target reallocation | E27: 180000
A28: Total reinvested | E28: =E22 -> 180000
A29: Check: reinvested vs target | E29: =E28-E27 -> 0
A30: Funded by: proceeds from October sales | E30: =E10 -> 78936.6
A31: Funded by: additional cash | E31: =E28-E30 -> 101063.4

Sheet Allocation
A1: Portfolio Allocation
A2: Market value weights, today vs after the October rebalance
A3: Color key: Hard-coded input Formula Link to another tab Link to external file
A5: 1 · Asset Class
A6: Asset Class | B6: Current MV | C6: Current % | D6: Sold | E6: Added | F6: Pro Forma MV | G6: Pro Forma % | H6: Change
A7: Equity ETF | B7: =SUMIFS(OpenPosition_10_28_2026!$L$6:$L$60,OpenPosition_10_28_2026!$C$6:$C$60,$A7) -> 921563.04 | C7: =IFERROR(B7/B$14,0) -> 0.64176331 | D7: =-SUMIFS(OpenPosition_10_28_2026!$L$6:$L$60,OpenPosition_10_28_2026!$C$6:$C$60,$A7,OpenPosition_10_28_2026!$E$6:$E$60,"Sold Oct-26") -> -20442.4 | E7: =SUMIFS('Rebalance Oct-26'!$E$15:$E$21,'Rebalance Oct-26'!$B$15:$B$21,$A7) -> 120000 | F7: =B7+D7+E7 -> 1021120.6 | G7: =IFERROR(F7/F$14,0) -> 0.68249225 | H7: =G7-C7 -> 0.040728933
A8: Single Stock | B8: =SUMIFS(OpenPosition_10_28_2026!$L$6:$L$60,OpenPosition_10_28_2026!$C$6:$C$60,$A8) -> 112684.34 | C8: =IFERROR(B8/B$14,0) -> 0.078471762 | D8: =-SUMIFS(OpenPosition_10_28_2026!$L$6:$L$60,OpenPosition_10_28_2026!$C$6:$C$60,$A8,OpenPosition_10_28_2026!$E$6:$E$60,"Sold Oct-26") -> -41039 | E8: =SUMIFS('Rebalance Oct-26'!$E$15:$E$21,'Rebalance Oct-26'!$B$15:$B$21,$A8) -> 0 | F8: =B8+D8+E8 -> 71645.34 | G8: =IFERROR(F8/F$14,0) -> 0.047886006 | H8: =G8-C8 -> -0.030585756
A9: Fixed Income | B9: =SUMIFS(OpenPosition_10_28_2026!$L$6:$L$60,OpenPosition_10_28_2026!$C$6:$C$60,$A9) -> 103692.91 | C9: =IFERROR(B9/B$14,0) -> 0.072210262 | D9: =-SUMIFS(OpenPosition_10_28_2026!$L$6:$L$60,OpenPosition_10_28_2026!$C$6:$C$60,$A9,OpenPosition_10_28_2026!$E$6:$E$60,"Sold Oct-26") -> 0 | E9: =SUMIFS('Rebalance Oct-26'!$E$15:$E$21,'Rebalance Oct-26'!$B$15:$B$21,$A9) -> 0 | F9: =B9+D9+E9 -> 103692.91 | G9: =IFERROR(F9/F$14,0) -> 0.069305827 | H9: =G9-C9 -> -0.002904435
A10: Digital Assets | B10: =SUMIFS(OpenPosition_10_28_2026!$L$6:$L$60,OpenPosition_10_28_2026!$C$6:$C$60,$A10) -> 171695.56 | C10: =IFERROR(B10/B$14,0) -> 0.11956633 | D10: =-SUMIFS(OpenPosition_10_28_2026!$L$6:$L$60,OpenPosition_10_28_2026!$C$6:$C$60,$A10,OpenPosition_10_28_2026!$E$6:$E$60,"Sold Oct-26") -> 0 | E10: =SUMIFS('Rebalance Oct-26'!$E$15:$E$21,'Rebalance Oct-26'!$B$15:$B$21,$A10) -> 0 | F10: =B10+D10+E10 -> 171695.56 | G10: =IFERROR(F10/F$14,0) -> 0.11475714 | H10: =G10-C10 -> -0.0048091868
A11: Leveraged / Inverse ETF | B11: =SUMIFS(OpenPosition_10_28_2026!$L$6:$L$60,OpenPosition_10_28_2026!$C$6:$C$60,$A11) -> 98965 | C11: =IFERROR(B11/B$14,0) -> 0.06891781 | D11: =-SUMIFS(OpenPosition_10_28_2026!$L$6:$L$60,OpenPosition_10_28_2026!$C$6:$C$60,$A11,OpenPosition_10_28_2026!$E$6:$E$60,"Sold Oct-26") -> -58340 | E11: =SUMIFS('Rebalance Oct-26'!$E$15:$E$21,'Rebalance Oct-26'!$B$15:$B$21,$A11) -> 0 | F11: =B11+D11+E11 -> 40625 | G11: =IFERROR(F11/F$14,0) -> 0.027152764 | H11: =G11-C11 -> -0.041765046
A12: Options | B12: =SUMIFS(OpenPosition_10_28_2026!$L$6:$L$60,OpenPosition_10_28_2026!$C$6:$C$60,$A12) -> 27385 | C12: =IFERROR(B12/B$14,0) -> 0.019070522 | D12: =-SUMIFS(OpenPosition_10_28_2026!$L$6:$L$60,OpenPosition_10_28_2026!$C$6:$C$60,$A12,OpenPosition_10_28_2026!$E$6:$E$60,"Sold Oct-26") -> 0 | E12: =SUMIFS('Rebalance Oct-26'!$E$15:$E$21,'Rebalance Oct-26'!$B$15:$B$21,$A12) -> 0 | F12: =B12+D12+E12 -> 27385 | G12: =IFERROR(F12/F$14,0) -> 0.018303469 | H12: =G12-C12 -> -0.00076705293
A13: Private Markets | B13: =SUMIFS(OpenPosition_10_28_2026!$L$6:$L$60,OpenPosition_10_28_2026!$C$6:$C$60,$A13) -> 0 | C13: =IFERROR(B13/B$14,0) -> 0 | D13: =-SUMIFS(OpenPosition_10_28_2026!$L$6:$L$60,OpenPosition_10_28_2026!$C$6:$C$60,$A13,OpenPosition_10_28_2026!$E$6:$E$60,"Sold Oct-26") -> 0 | E13: =SUMIFS('Rebalance Oct-26'!$E$15:$E$21,'Rebalance Oct-26'!$B$15:$B$21,$A13) -> 60000 | F13: =B13+D13+E13 -> 60000 | G13: =IFERROR(F13/F$14,0) -> 0.040102543 | H13: =G13-C13 -> 0.040102543
A14: Total | B14: =SUM(B7:B13) -> 1435985.9 | C14: =SUM(C7:C13) -> 1 | D14: =SUM(D7:D13) -> -119821.4 | E14: =SUM(E7:E13) -> 180000 | F14: =SUM(F7:F13) -> 1496164.5 | G14: =SUM(G7:G13) -> 1 | H14: =SUM(H7:H13) -> 0
A17: 2 · Sector
A18: Sector | B18: Current MV | C18: Current % | D18: Sold | E18: Added | F18: Pro Forma MV | G18: Pro Forma % | H18: Change
A19: US Broad Market | B19: =SUMIFS(OpenPosition_10_28_2026!$L$6:$L$60,OpenPosition_10_28_2026!$D$6:$D$60,$A19) -> 314964.5 | C19: =IFERROR(B19/B$35,0) -> 0.21933677 | D19: =-SUMIFS(OpenPosition_10_28_2026!$L$6:$L$60,OpenPosition_10_28_2026!$D$6:$D$60,$A19,OpenPosition_10_28_2026!$E$6:$E$60,"Sold Oct-26") -> 0 | E19: =SUMIFS('Rebalance Oct-26'!$E$15:$E$21,'Rebalance Oct-26'!$C$15:$C$21,$A19) -> 0 | F19: =B19+D19+E19 -> 314964.5 | G19: =IFERROR(F19/F$35,0) -> 0.21051463 | H19: =G19-C19 -> -0.008822145
A20: US Small Cap | B20: =SUMIFS(OpenPosition_10_28_2026!$L$6:$L$60,OpenPosition_10_28_2026!$D$6:$D$60,$A20) -> 217815.44 | C20: =IFERROR(B20/B$35,0) -> 0.15168356 | D20: =-SUMIFS(OpenPosition_10_28_2026!$L$6:$L$60,OpenPosition_10_28_2026!$D$6:$D$60,$A20,OpenPosition_10_28_2026!$E$6:$E$60,"Sold Oct-26") -> -58340 | E20: =SUMIFS('Rebalance Oct-26'!$E$15:$E$21,'Rebalance Oct-26'!$C$15:$C$21,$A20) -> 0 | F20: =B20+D20+E20 -> 159475.44 | G20: =IFERROR(F20/F$35,0) -> 0.10658951 | H20: =G20-C20 -> -0.045094043
A21: International / EM | B21: =SUMIFS(OpenPosition_10_28_2026!$L$6:$L$60,OpenPosition_10_28_2026!$D$6:$D$60,$A21) -> 117515 | C21: =IFERROR(B21/B$35,0) -> 0.081835764 | D21: =-SUMIFS(OpenPosition_10_28_2026!$L$6:$L$60,OpenPosition_10_28_2026!$D$6:$D$60,$A21,OpenPosition_10_28_2026!$E$6:$E$60,"Sold Oct-26") -> 0 | E21: =SUMIFS('Rebalance Oct-26'!$E$15:$E$21,'Rebalance Oct-26'!$C$15:$C$21,$A21) -> 0 | F21: =B21+D21+E21 -> 117515 | G21: =IFERROR(F21/F$35,0) -> 0.078544173 | H21: =G21-C21 -> -0.0032915912
A22: Technology | B22: =SUMIFS(OpenPosition_10_28_2026!$L$6:$L$60,OpenPosition_10_28_2026!$D$6:$D$60,$A22) -> 63512.47 | C22: =IFERROR(B22/B$35,0) -> 0.044229175 | D22: =-SUMIFS(OpenPosition_10_28_2026!$L$6:$L$60,OpenPosition_10_28_2026!$D$6:$D$60,$A22,OpenPosition_10_28_2026!$E$6:$E$60,"Sold Oct-26") -> -20442.4 | E22: =SUMIFS('Rebalance Oct-26'!$E$15:$E$21,'Rebalance Oct-26'!$C$15:$C$21,$A22) -> 30000 | F22: =B22+D22+E22 -> 73070.07 | G22: =IFERROR(F22/F$35,0) -> 0.048838261 | H22: =G22-C22 -> 0.0046090857
A23: Financials | B23: =SUMIFS(OpenPosition_10_28_2026!$L$6:$L$60,OpenPosition_10_28_2026!$D$6:$D$60,$A23) -> 149462.17 | C23: =IFERROR(B23/B$35,0) -> 0.10408332 | D23: =-SUMIFS(OpenPosition_10_28_2026!$L$6:$L$60,OpenPosition_10_28_2026!$D$6:$D$60,$A23,OpenPosition_10_28_2026!$E$6:$E$60,"Sold Oct-26") -> 0 | E23: =SUMIFS('Rebalance Oct-26'!$E$15:$E$21,'Rebalance Oct-26'!$C$15:$C$21,$A23) -> 20000 | F23: =B23+D23+E23 -> 169462.17 | G23: =IFERROR(F23/F$35,0) -> 0.1132644 | H23: =G23-C23 -> 0.0091810841
A24: Industrials | B24: =SUMIFS(OpenPosition_10_28_2026!$L$6:$L$60,OpenPosition_10_28_2026!$D$6:$D$60,$A24) -> 91529.8 | C24: =IFERROR(B24/B$35,0) -> 0.063740043 | D24: =-SUMIFS(OpenPosition_10_28_2026!$L$6:$L$60,OpenPosition_10_28_2026!$D$6:$D$60,$A24,OpenPosition_10_28_2026!$E$6:$E$60,"Sold Oct-26") -> 0 | E24: =SUMIFS('Rebalance Oct-26'!$E$15:$E$21,'Rebalance Oct-26'!$C$15:$C$21,$A24) -> 60000 | F24: =B24+D24+E24 -> 151529.8 | G24: =IFERROR(F24/F$35,0) -> 0.10127884 | H24: =G24-C24 -> 0.037538797
A25: Health Care | B25: =SUMIFS(OpenPosition_10_28_2026!$L$6:$L$60,OpenPosition_10_28_2026!$D$6:$D$60,$A25) -> 48314 | C25: =IFERROR(B25/B$35,0) -> 0.033645178 | D25: =-SUMIFS(OpenPosition_10_28_2026!$L$6:$L$60,OpenPosition_10_28_2026!$D$6:$D$60,$A25,OpenPosition_10_28_2026!$E$6:$E$60,"Sold Oct-26") -> -41039 | E25: =SUMIFS('Rebalance Oct-26'!$E$15:$E$21,'Rebalance Oct-26'!$C$15:$C$21,$A25) -> 25000 | F25: =B25+D25+E25 -> 32275 | G25: =IFERROR(F25/F$35,0) -> 0.021571826 | H25: =G25-C25 -> -0.012073352
A26: Consumer Staples | B26: =SUMIFS(OpenPosition_10_28_2026!$L$6:$L$60,OpenPosition_10_28_2026!$D$6:$D$60,$A26) -> 76440 | C26: =IFERROR(B26/B$35,0) -> 0.053231722 | D26: =-SUMIFS(OpenPosition_10_28_2026!$L$6:$L$60,OpenPosition_10_28_2026!$D$6:$D$60,$A26,OpenPosition_10_28_2026!$E$6:$E$60,"Sold Oct-26") -> 0 | E26: =SUMIFS('Rebalance Oct-26'!$E$15:$E$21,'Rebalance Oct-26'!$C$15:$C$21,$A26) -> 0 | F26: =B26+D26+E26 -> 76440 | G26: =IFERROR(F26/F$35,0) -> 0.05109064 | H26: =G26-C26 -> -0.0021410818
A27: Consumer Discretionary | B27: =SUMIFS(OpenPosition_10_28_2026!$L$6:$L$60,OpenPosition_10_28_2026!$D$6:$D$60,$A27) -> 9544.6 | C27: =IFERROR(B27/B$35,0) -> 0.0066467229 | D27: =-SUMIFS(OpenPosition_10_28_2026!$L$6:$L$60,OpenPosition_10_28_2026!$D$6:$D$60,$A27,OpenPosition_10_28_2026!$E$6:$E$60,"Sold Oct-26") -> 0 | E27: =SUMIFS('Rebalance Oct-26'!$E$15:$E$21,'Rebalance Oct-26'!$C$15:$C$21,$A27) -> 0 | F27: =B27+D27+E27 -> 9544.6 | G27: =IFERROR(F27/F$35,0) -> 0.0063793789 | H27: =G27-C27 -> -0.00026734392
A28: Communication Services | B28: =SUMIFS(OpenPosition_10_28_2026!$L$6:$L$60,OpenPosition_10_28_2026!$D$6:$D$60,$A28) -> 4719.4 | C28: =IFERROR(B28/B$35,0) -> 0.0032865226 | D28: =-SUMIFS(OpenPosition_10_28_2026!$L$6:$L$60,OpenPosition_10_28_2026!$D$6:$D$60,$A28,OpenPosition_10_28_2026!$E$6:$E$60,"Sold Oct-26") -> 0 | E28: =SUMIFS('Rebalance Oct-26'!$E$15:$E$21,'Rebalance Oct-26'!$C$15:$C$21,$A28) -> 0 | F28: =B28+D28+E28 -> 4719.4 | G28: =IFERROR(F28/F$35,0) -> 0.0031543324 | H28: =G28-C28 -> -0.00013219023
A29: Real Estate | B29: =SUMIFS(OpenPosition_10_28_2026!$L$6:$L$60,OpenPosition_10_28_2026!$D$6:$D$60,$A29) -> 24492.5 | C29: =IFERROR(B29/B$35,0) -> 0.017056227 | D29: =-SUMIFS(OpenPosition_10_28_2026!$L$6:$L$60,OpenPosition_10_28_2026!$D$6:$D$60,$A29,OpenPosition_10_28_2026!$E$6:$E$60,"Sold Oct-26") -> 0 | E29: =SUMIFS('Rebalance Oct-26'!$E$15:$E$21,'Rebalance Oct-26'!$C$15:$C$21,$A29) -> 15000 | F29: =B29+D29+E29 -> 39492.5 | G29: =IFERROR(F29/F$35,0) -> 0.026395828 | H29: =G29-C29 -> 0.0093396018
A30: Materials | B30: =SUMIFS(OpenPosition_10_28_2026!$L$6:$L$60,OpenPosition_10_28_2026!$D$6:$D$60,$A30) -> 0 | C30: =IFERROR(B30/B$35,0) -> 0 | D30: =-SUMIFS(OpenPosition_10_28_2026!$L$6:$L$60,OpenPosition_10_28_2026!$D$6:$D$60,$A30,OpenPosition_10_28_2026!$E$6:$E$60,"Sold Oct-26") -> 0 | E30: =SUMIFS('Rebalance Oct-26'!$E$15:$E$21,'Rebalance Oct-26'!$C$15:$C$21,$A30) -> 30000 | F30: =B30+D30+E30 -> 30000 | G30: =IFERROR(F30/F$35,0) -> 0.020051272 | H30: =G30-C30 -> 0.020051272
... A34: Other | B34: =SUMIFS(OpenPosition_10_28_2026!$L$6:$L$60,OpenPosition_10_28_2026!$D$6:$D$60,$A34) -> 1662.5 | C34: =IFERROR(B34/B$35,0) -> 0.0011577412 | D34: =-SUMIFS(OpenPosition_10_28_2026!$L$6:$L$60,OpenPosition_10_28_2026!$D$6:$D$60,$A34,OpenPosition_10_28_2026!$E$6:$E$60,"Sold Oct-26") -> 0 | E34: =SUMIFS('Rebalance Oct-26'!$E$15:$E$21,'Rebalance Oct-26'!$C$15:$C$21,$A34) -> 0 | F34: =B34+D34+E34 -> 1662.5 | G34: =IFERROR(F34/F$35,0) -> 0.0011111746 | H34: =G34-C34 -> -4.6566569e-05
A35: Total | B35: =SUM(B19:B34) -> 1435985.9 | C35: =SUM(C19:C34) -> 1 | D35: =SUM(D19:D34) -> -119821.4 | E35: =SUM(E19:E34) -> 180000 | F35: =SUM(F19:F34) -> 1496164.5 | G35: =SUM(G19:G34) -> 1 | H35: =SUM(H19:H34) -> -3.512815e-17
A36: Current MV = MarketValue from the positions tab (SOXX short counted at gross value). Sold = highlighted rows. Added = Rebalance tab.
